construct_gallery/__init__.py
construct_gallery/__main__.py
construct_gallery/__version__.py
construct_gallery/allow_python_expr_plugin.py
construct_gallery/bleak_scanner_construct.py
construct_gallery/config_editor.py
construct_gallery/construct_gallery.py
construct_gallery/decimal_convert_plugin.py
construct_gallery/pyshell_plugin.py
construct_gallery/string_convert_plugin.py
construct_gallery/wx_logging_plugin.py
construct_gallery-1.3.0.dist-info/LICENSE
construct_gallery-1.3.0.dist-info/METADATA
construct_gallery-1.3.0.dist-info/WHEEL
construct_gallery-1.3.0.dist-info/entry_points.txt
construct_gallery-1.3.0.dist-info/top_level.txt
construct_gallery-1.3.0.dist-info/RECORD
