Metadata-Version: 2.1
Name: construct-gallery
Version: 1.3.0
Summary: construct-gallery GUI (based on wxPython) and development modules
Home-page: https://github.com/Ircama/construct-gallery
Author: Ircama
License: CC-BY-NC-SA-4.0
Keywords: construct-gallery,construct-editor,module,gui,wx,wxpython,widget,binary,editorconstruct,bleak,BLE,bluetooth,plugin
Classifier: License :: Other/Proprietary License
Classifier: Topic :: Software Development :: Libraries :: Python Modules
Classifier: Programming Language :: Python :: 3 :: Only
Classifier: Programming Language :: Python :: Implementation :: CPython
Classifier: Development Status :: 5 - Production/Stable
Classifier: Typing :: Typed
Classifier: Intended Audience :: Developers
Requires-Python: >=3.8
License-File: LICENSE
Requires-Dist: construct-editor
